{
    "shoes": {
        "items": [
            {
            "id": 0,
                "name": "Sneakerși waterproof",
                "price": 345,
                "currency": "LEI",
                "image": "https://imgur.com/pDJUfoV.jpg",
                "size": "Toate marimile",
                "colour": "Negru",
                "material": "Piele",
                "brand": "Maximo Dute",
                "description": "Sneakerși din piele cu talpă puțin tocită, dar încă bună, recomand, 5000km."
            },
            {
                "id": 1,
                "name": "Sneakerși piele Massimo Dutti",
                "price": 135,
                "currency": "LEI",
                "image": "https://i.imgur.com/Rz8lVQa.jpg",
                "size": 45,
                "colour": "Negru",
                "material": "Piele",
                "brand": "Massimo Dutti",
                "description": "Sneakerși din piele cu talpă inițial albă, din colecția de toamnă-iarnă 2019, Massimo Dutti."
            },
            {
                "id": 2,
                "name": "Teniși negri Polo Ralph Lauren",
                "price": 100,
                "currency": "LEI",
                "image": "https://i.imgur.com/Og3Oh24.jpg",
                "size": 45,
                "colour": "Negru",
                "material": "Pânză",
                "brand": "Polo Ralph Lauren",
                "description": "Teniși din pânză cu talpă inițial albă, din colecția de primăvară-vară 2019, Fashion Days."
            },
            {
                "id": 3,
                "name": "Ghete din piele maro Massimo",
                "price": 185,
                "currency": "LEI",
                "image": "https://i.imgur.com/zoqSu87.jpg",
                "size": 45,
                "colour": "Maro",
                "material": "Piele",
                "brand": "Massimo Dutti",
                "description": "Ghete maro din piele, din colecția de toamnă-iarnă 2017, Massimo Dutti."
            }
        ],
        "image": "https://imgur.com/1PeafzS.jpg",
        "name": "Încălțăminte",
        "description": "Ghete, pantofi, sneakerși: finețe garantată!"
    },
    "sweaters": {
        "items": [
            {
                "id": 4,
                "name": "Pulovăr finuț cu guler",
                "price": 95,
                "currency": "LEI",
                "image": "https://i.imgur.com/6afzuEr.jpg",
                "size": "L",
                "colour": "Maro",
                "material": "Cașmir",
                "brand": "DS Damat",
                "description": "Pulovăr din cașmir, slim fit, colecția toamnă-iarnă 2019, DS Damat."
            },
            {
                "id": 5,
                "name": "Pulovăr multicolor",
                "price": 105,
                "currency": "LEI",
                "image": "https://i.imgur.com/s0VytKc.jpg",
                "size": "L",
                "colour": "Multicolor",
                "material": "Bumbac",
                "brand": "McNeal",
                "description": "Pulovăr multicolor, colecția toamnă-iarnă 209, McNeal."
            },
            {
                "id": 6,
                "name": "Pulovăr fain",
                "price": 163,
                "currency": "LEI",
                "image": "https://imgur.com/wprlRbC.jpg",
                "size": "L",
                "colour": "Deocamdată gALBEN",
                "material": "Lână",
                "brand": "Necunoscut",
                "description": "Pulovăr din lână, în carouri, colecția din ultima prezentare de modă a lui Botezatu 2019, EXCLUSIV."
            },
            {
                "id": 7,
                "name": "Pulovăr din lână",
                "price": 160,
                "currency": "LEI",
                "image": "https://i.imgur.com/dTcMbHT.jpg",
                "size": "L",
                "colour": "Crem",
                "material": "Lână",
                "brand": "Massimo Dutti",
                "description": "Pulovăr din lână cu model, colecția toamnă-iarnă 2019, Massimo Dutti."
            },
            {
                "id": 23,
                "name": "Pulovăr șucar",
                "price": 200,
                "currency": "LEI",
                "image": "https://i.imgur.com/poAoDfq.jpg",
                "size": "M",
                "colour": "Modelat",
                "material": "Mișto",
                "brand": "Hugo",
                "description": "Pulovăr din lână cu model, colecția toamnă-iarnă 2023, ceva de nemaipomenit."
            },
            {
                "id": 24,
                "name": "Pulovăr de mers pe munte",
                "price": 160,
                "currency": "LEI",
                "image": "https://i.imgur.com/bzU1iAH.jpg",
                "size": "L",
                "colour": "Maro",
                "material": "Poliester",
                "brand": "MilitaryFactory",
                "description": "Puloverul perfect pentru drumeții și pentru a te lua la trântă cu ursul.."
            }
        ],
        "image": "https://i.imgur.com/5JcorQf.jpg",
        "name": "Pulovere",
        "description": "Pulovărașe elegănțele, slim, clasă superioară."
    },
    "pants": {
        "items": [
            {
                "id": 8,
                "name": "Blugi bleumarin slim fit",
                "price": 35,
                "currency": "LEI",
                "image": "https://i.imgur.com/VhpATO8.jpg",
                "size": "34",
                "colour": "Bleumarin închis",
                "material": "Blug",
                "brand": "DS Damat",
                "description": "Blugi bleumarin, slim fit, colecția primăvară-vară 2019, DS Damat."
            },
            {
                "id": 9,
                "name": "Blugi negri slim fit",
                "price": 40,
                "currency": "LEI",
                "image": "https://i.imgur.com/weiI07t.jpg",
                "size": "34",
                "colour": "Negru-gri",
                "material": "Blug",
                "brand": "DS Damat",
                "description": "Blugi negri, slim fit, colecția toamnă-iarnă 2019, DS Damat."
            },
            {

                "id": 10,
                "name": "Blugi perfecti pentru tine",
                "price": 100,
                "currency": "LEI",
                "image": "https://i.imgur.com/nVgAKol.jpg",
                "size": "38",
                "colour": "Abastru albatros",
                "material": "Blug",
                "brand": "De firma",
                "description": "Cel mai bun blug de firmă pe care-l poți avea"
            },
            {

                "id": 19,
                "name": "Pantaloni de șmecheraș",
                "price": 142,
                "currency": "LEI",
                "image": "https://i.imgur.com/nEKO0ct.jpg",
                "size": "43",
                "colour": "Alb cremos",
                "material": "Tercot",
                "brand": "Original",
                "description": "Cea mai tare achiziție pe care o poți avea."
            },
            {

                "id": 20,
                "name": "Pantaloni lărguți",
                "price": 230,
                "currency": "LEI",
                "image": "https://i.imgur.com/wqYL6jj.jpg",
                "size": "40",
                "colour": "Verde de Merlot",
                "material": "Cartonită",
                "brand": "Luxor",
                "description": "Cu pantalonii lărguți și drăguți nu vei mai simți niciodată frigul, iar designul lor îți vor oferi lejeritate"
            },
            {

                "id": 21,
                "name": "Pantaloni de MachoMan",
                "price": 300,
                "currency": "LEI",
                "image": "https://i.imgur.com/IUxIqrz.jpg",
                "size": "38",
                "colour": "Un crem",
                "material": "Satin",
                "brand": "Ca lumea",
                "description": "Cei mai indicați pantaloni de agățat."
            },
            {

                "id": 22,
                "name": "Dătători pe spate",
                "price": 400,
                "currency": "LEI",
                "image": "https://i.imgur.com/XV5qd12.jpg",
                "size": "40",
                "colour": "Alb ca zăpada",
                "material": "Catifea",
                "brand": "Italienesc",
                "description": "Cu pantalonii dătători pe spate, vei simți că lumea pică în urma ta pe stradă."
            }
        ],
        "image": "https://i.imgur.com/peOY9ki.jpg",
        "name": "Pantaloni/blugi",
        "description": "Jeanși și pantaloni pentru baieții care și-o ard patroni!"
    },
    "jackets": {
        "items": [
            {
                "id": 11,
                "name": "Haină lungă din lână virgină",
                "price": 210,
                "currency": "LEI",
                "image": "https://i.imgur.com/IXrZitQ.jpg",
                "size": "L",
                "colour": "Gri închis",
                "material": "Lână virgină",
                "brand": "Peek and Cloppenburg",
                "description": "Haină lungă din lână virgină, colecția toamnă-iarnă 2018, Peek and Cloppenburg."
            },
            {
                "id": 12,
                "name": "Geacă bleumarin cu glugă detașabilă",
                "price": 250,
                "currency": "LEI",
                "image": "https://i.imgur.com/eCZd7PU.jpg",
                "size": "L",
                "colour": "Bleumarin",
                "material": "Poliester",
                "brand": "DS Damat",
                "description": "Geacă bleumarin cu glugă detașabilă, colecția toamnă-iarnă 2019, DS Damat."
            }
        ],
        "image": "https://i.imgur.com/fwG2JNf.jpg",
        "name": "Geci/Haine",
        "description": "Confortabile, călduroase și nu arăți ca un cartof!"
    },
    "tshirts": {
        "items": [
            {
                "id": 13,
                "name": "Tricou în dungi",
                "price": 90,
                "currency": "LEI",
                "image": "https://i.imgur.com/BWvzCwB.jpg",
                "size": "L",
                "colour": "Multicolor",
                "material": "Bumbac",
                "brand": "Lacoste",
                "description": "Tricou în dungi, colecția primăvară-vară 2019, Lacoste."
            },
            {
                "id": 14,
                "name": "Tricou de golani",
                "price": 210,
                "currency": "LEI",
                "image":"https://i.imgur.com/ARMRPOH.jpg" ,
                "size": "L",
                "colour": "Negrtu cu imprimeu",
                "material": "Golanesc",
                "brand": "The thief",
                "description": "Tricou de golani, folosit doar pentru jafuri calificate."
            },
            {
                "id": 15,
                "name": "Tricou original BVB cu autograf",
                "price": 199,
                "currency": "LEI",
                "image": "https://i.imgur.com/etIsbHV.jpg",
                "size": "L",
                "colour": "Galben-Negru",
                "material": "Poliester",
                "brand": "Puma",
                "description": "Tricoul purtat de Borussia Dortmund în sezonul competițional 2018-2019, cu numarul 7 și numele 'SANCHO'. Tricoul este semnat de portarul Borussiei, Roman Burki."
            },
            {

                "id": 16,
                "name": "Giccu's original",
                "price": 165,
                "currency": "LEI",
                "image": "https://imgur.com/HMxAzXJ.jpg",
                "size": 45,
                "colour": "Negru",
                "material": "Tricou din cauciuc",
                "brand": "Gicutza",
                "description": "Cel mai tare tricou de firmă, de la nenea Giccu din ogradă"
                
            }
        ],
        "image": "https://i.imgur.com/qCbirys.jpg",
        "name": "Tricouri",
        "description": "Și de băiețeală și de sport."
    },
    "accesories": {
        "items": [
            {
                "id": 17,
                "name": "Fular TJ cu două fețe",
                "price": 85,
                "currency": "LEI",
                "image": "https://i.imgur.com/rSVUiLO.jpg",
                "size": "Universal",
                "colour": "Gri-Bleumarin",
                "material": "Cașmir",
                "brand": "Trussardi Jeans",
                "description": "Fular cu imprimeu, din colecția toamnă-iarnă 2018, Trussardi Jeans."
            },
            {
                "id": 18,
                "name": "Mănuși din piele",
                "price": 60,
                "currency": "LEI",
                "image": "https://i.imgur.com/LbjGaZ1.jpg",
                "size": "L",
                "colour": "Negru",
                "material": "Piele",
                "brand": "DS Damat",
                "description": "Mănuși din piele, cu model, din colecția toamnă-iarnă 2018, DS Damat."
            },
            {
                "id": 25,
                "name": "Brățară din granit",
                "price": 80,
                "currency": "LEI",
                "image": "https://i.imgur.com/XcPSorL.jpg",
                "size": "L",
                "colour": "Maro",
                "material": "Granit",
                "brand": "Casio",
                "description": "Brățara perfectă pentru a părea un băiat cu mâna mare.."
            },
            {
                "id": 26,
                "name": "Brățară cu pietricele din sulf",
                "price": 50,
                "currency": "LEI",
                "image": "https://i.imgur.com/MNNTEaY.jpg",
                "size": "S",
                "colour": "Negru",
                "material": "Sulf",
                "brand": "Pandora",
                "description": "Cu brățărica drăguțică îți vei completa perfect ținuta."
            }
        ],
        "image": "https://i.imgur.com/5NnNg7m.jpg",
        "name": "Accesorii",
        "description": "Fulare, căciuli, mănuși: nu mai sta pe gânduri, cumpără-le acuși!"
    }
}